vocabuilder/__init__.py
vocabuilder/add_window.py
vocabuilder/commandline.py
vocabuilder/config.py
vocabuilder/constants.py
vocabuilder/csv_helpers.py
vocabuilder/data/__init__.py
vocabuilder/data/default_config.ini
vocabuilder/database.py
vocabuilder/exceptions.py
vocabuilder/firebase_database.py
vocabuilder/local_database.py
vocabuilder/main_window.py
vocabuilder/mixins.py
vocabuilder/modify_window.py
vocabuilder/py.typed
vocabuilder/select_voca.py
vocabuilder/test_window.py
vocabuilder/type_aliases.py
vocabuilder/view_window.py
vocabuilder/vocabuilder.py
vocabuilder/widgets.py
vocabuilder-0.1.19.dist-info/LICENSE
vocabuilder-0.1.19.dist-info/METADATA
vocabuilder-0.1.19.dist-info/WHEEL
vocabuilder-0.1.19.dist-info/entry_points.txt
vocabuilder-0.1.19.dist-info/RECORD
